ibonds/__init__.py
ibonds/interest_rates.yaml
ibonds-1.0.7.dist-info/licenses/LICENSE
ibonds-1.0.7.dist-info/METADATA
ibonds-1.0.7.dist-info/WHEEL
ibonds-1.0.7.dist-info/top_level.txt
ibonds-1.0.7.dist-info/RECORD
