Metadata-Version: 2.4
Name: ibonds
Version: 1.0.7
Summary: Library to calculate the current value of a Series I Savings bond (I Bond)
Home-page: https://github.com/sarvjeets/ibonds
Author: Sarvjeet Singh
Author-email: sarvjeet@gmail.com
License: MIT
Platform: any
Classifier: Development Status :: 5 - Production/Stable
Classifier: Operating System :: OS Independent
Classifier: Programming Language :: Python :: 3
Requires-Python: >=3.7
License-File: LICENSE
Requires-Dist: PyYAML~=6.0
Requires-Dist: requests~=2.28
Dynamic: author
Dynamic: author-email
Dynamic: classifier
Dynamic: description
Dynamic: description-content-type
Dynamic: home-page
Dynamic: license
Dynamic: license-file
Dynamic: platform
Dynamic: requires-dist
Dynamic: requires-python
Dynamic: summary
